[
    {
        "name": "PA(36:01)",
        "adduct": "[M+Na]+",
        "mz": 725.5093,
        "ccs": 273.4
    },
    {
        "name": "PA(36:02)",
        "adduct": "[M+Na]+",
        "mz": 723.4907,
        "ccs": 272.25
    },
    {
        "name": "PA(36:03)",
        "adduct": "[M+Na]+",
        "mz": 721.479,
        "ccs": 270.97
    },
    {
        "name": "PA(36:04)",
        "adduct": "[M+Na]+",
        "mz": 719.461,
        "ccs": 268.39
    },
    {
        "name": "PA(38:02)",
        "adduct": "[M+Na]+",
        "mz": 751.5251,
        "ccs": 279.74
    },
    {
        "name": "PA(38:03)",
        "adduct": "[M+Na]+",
        "mz": 749.5084,
        "ccs": 277.43
    },
    {
        "name": "PA(38:04)",
        "adduct": "[M+Na]+",
        "mz": 747.4962,
        "ccs": 276.54
    },
    {
        "name": "PA(40:05)",
        "adduct": "[M+Na]+",
        "mz": 773.5092,
        "ccs": 281.79
    },
    {
        "name": "PA(35:01)",
        "adduct": "[M+2Na-H]+",
        "mz": 733.4761,
        "ccs": 271.84
    },
    {
        "name": "PA(35:02)",
        "adduct": "[M+2Na-H]+",
        "mz": 731.4598,
        "ccs": 270.0
    },
    {
        "name": "PA(36:01)",
        "adduct": "[M+2Na-H]+",
        "mz": 747.489,
        "ccs": 274.66
    },
    {
        "name": "PA(36:02)",
        "adduct": "[M+2Na-H]+",
        "mz": 745.4764,
        "ccs": 273.1
    },
    {
        "name": "PA(36:03)",
        "adduct": "[M+2Na-H]+",
        "mz": 743.4609,
        "ccs": 271.74
    },
    {
        "name": "PA(36:04)",
        "adduct": "[M+2Na-H]+",
        "mz": 741.4407,
        "ccs": 270.03
    },
    {
        "name": "PA(36:05)",
        "adduct": "[M+2Na-H]+",
        "mz": 739.4246,
        "ccs": 269.3
    },
    {
        "name": "PA(38:03)",
        "adduct": "[M+2Na-H]+",
        "mz": 771.4933,
        "ccs": 279.8
    },
    {
        "name": "PA(38:04)",
        "adduct": "[M+2Na-H]+",
        "mz": 769.4743,
        "ccs": 276.1
    },
    {
        "name": "PA(40:05)",
        "adduct": "[M+2Na-H]+",
        "mz": 795.4929,
        "ccs": 283.07
    },
    {
        "name": "PA(40:06)",
        "adduct": "[M+2Na-H]+",
        "mz": 793.4762,
        "ccs": 280.58
    },
    {
        "name": "PE(34:01)",
        "adduct": "[M+H]+",
        "mz": 718.5401,
        "ccs": 270.06
    },
    {
        "name": "PE(34:02)",
        "adduct": "[M+H]+",
        "mz": 716.5251,
        "ccs": 268.45
    },
    {
        "name": "PE(34:03)",
        "adduct": "[M+H]+",
        "mz": 714.5092,
        "ccs": 265.93
    },
    {
        "name": "PE(36:01)",
        "adduct": "[M+H]+",
        "mz": 746.5693,
        "ccs": 277.02
    },
    {
        "name": "PE(36:02)",
        "adduct": "[M+H]+",
        "mz": 744.555,
        "ccs": 275.13
    },
    {
        "name": "PE(36:03)",
        "adduct": "[M+H]+",
        "mz": 742.5344,
        "ccs": 273.34
    },
    {
        "name": "PE(32:01)",
        "adduct": "[M+Na]+",
        "mz": 712.4898,
        "ccs": 268.62
    },
    {
        "name": "PE(34:01)",
        "adduct": "[M+Na]+",
        "mz": 740.52,
        "ccs": 276.03
    },
    {
        "name": "PE(34:02)",
        "adduct": "[M+Na]+",
        "mz": 738.5046,
        "ccs": 273.06
    },
    {
        "name": "PE(34:03)",
        "adduct": "[M+Na]+",
        "mz": 736.4875,
        "ccs": 271.73
    },
    {
        "name": "PE(35:01)",
        "adduct": "[M+Na]+",
        "mz": 754.5324,
        "ccs": 279.26
    },
    {
        "name": "PE(35:02)",
        "adduct": "[M+Na]+",
        "mz": 752.5173,
        "ccs": 275.61
    },
    {
        "name": "PE(36:01)",
        "adduct": "[M+Na]+",
        "mz": 768.5493,
        "ccs": 282.21
    },
    {
        "name": "PE(36:02)",
        "adduct": "[M+Na]+",
        "mz": 766.5357,
        "ccs": 279.88
    },
    {
        "name": "PE(36:03)",
        "adduct": "[M+Na]+",
        "mz": 764.5186,
        "ccs": 277.57
    },
    {
        "name": "PE(37:01)",
        "adduct": "[M+Na]+",
        "mz": 782.5646,
        "ccs": 284.35
    },
    {
        "name": "PE(37:02)",
        "adduct": "[M+Na]+",
        "mz": 780.5498,
        "ccs": 282.21
    },
    {
        "name": "PE(37:03)",
        "adduct": "[M+Na]+",
        "mz": 778.5323,
        "ccs": 280.15
    },
    {
        "name": "PE(38:01)",
        "adduct": "[M+Na]+",
        "mz": 796.5778,
        "ccs": 285.93
    },
    {
        "name": "PE(40:05)",
        "adduct": "[M+Na]+",
        "mz": 816.5485,
        "ccs": 289.38
    },
    {
        "name": "PE(42:08)",
        "adduct": "[M+Na]+",
        "mz": 838.5324,
        "ccs": 290.41
    },
    {
        "name": "PE(42:09)",
        "adduct": "[M+Na]+",
        "mz": 836.5174,
        "ccs": 288.64
    },
    {
        "name": "PE(34:01)",
        "adduct": "[M+K]+",
        "mz": 756.494,
        "ccs": 277.57
    },
    {
        "name": "PE(34:02)",
        "adduct": "[M+K]+",
        "mz": 754.478,
        "ccs": 274.83
    },
    {
        "name": "PE(35:02)",
        "adduct": "[M+K]+",
        "mz": 768.4932,
        "ccs": 277.37
    },
    {
        "name": "PE(36:02)",
        "adduct": "[M+K]+",
        "mz": 782.5084,
        "ccs": 280.72
    },
    {
        "name": "PE(36:03)",
        "adduct": "[M+K]+",
        "mz": 780.4947,
        "ccs": 278.94
    },
    {
        "name": "PE(36:04)",
        "adduct": "[M+K]+",
        "mz": 778.4773,
        "ccs": 277.24
    },
    {
        "name": "PE(36:05)",
        "adduct": "[M+K]+",
        "mz": 776.4612,
        "ccs": 274.4
    },
    {
        "name": "PE(38:04)",
        "adduct": "[M+K]+",
        "mz": 806.5066,
        "ccs": 284.45
    },
    {
        "name": "PE(38:05)",
        "adduct": "[M+K]+",
        "mz": 804.4934,
        "ccs": 282.77
    },
    {
        "name": "PE(42:07)",
        "adduct": "[M+K]+",
        "mz": 856.5194,
        "ccs": 291.12
    },
    {
        "name": "PE(32:01)",
        "adduct": "[M+2Na-H]+",
        "mz": 734.4695,
        "ccs": 268.9
    },
    {
        "name": "PE(34:01)",
        "adduct": "[M+2Na-H]+",
        "mz": 762.5032,
        "ccs": 275.64
    },
    {
        "name": "PE(34:02)",
        "adduct": "[M+2Na-H]+",
        "mz": 760.4866,
        "ccs": 273.28
    },
    {
        "name": "PE(34:03)",
        "adduct": "[M+2Na-H]+",
        "mz": 758.4697,
        "ccs": 271.16
    },
    {
        "name": "PE(35:01)",
        "adduct": "[M+2Na-H]+",
        "mz": 776.5173,
        "ccs": 279.57
    },
    {
        "name": "PE(36:01)",
        "adduct": "[M+2Na-H]+",
        "mz": 790.5353,
        "ccs": 283.74
    },
    {
        "name": "PE(36:02)",
        "adduct": "[M+2Na-H]+",
        "mz": 788.5188,
        "ccs": 281.26
    },
    {
        "name": "PE(36:03)",
        "adduct": "[M+2Na-H]+",
        "mz": 786.5034,
        "ccs": 279.42
    },
    {
        "name": "PE(36:04)",
        "adduct": "[M+2Na-H]+",
        "mz": 784.4869,
        "ccs": 277.05
    },
    {
        "name": "PE(37:01)",
        "adduct": "[M+2Na-H]+",
        "mz": 804.5508,
        "ccs": 286.74
    },
    {
        "name": "PE(37:02)",
        "adduct": "[M+2Na-H]+",
        "mz": 802.5309,
        "ccs": 285.18
    },
    {
        "name": "PE(37:03)",
        "adduct": "[M+2Na-H]+",
        "mz": 800.5205,
        "ccs": 282.12
    },
    {
        "name": "PE(38:02)",
        "adduct": "[M+2Na-H]+",
        "mz": 816.5476,
        "ccs": 288.8
    },
    {
        "name": "PE(38:03)",
        "adduct": "[M+2Na-H]+",
        "mz": 814.5341,
        "ccs": 286.46
    },
    {
        "name": "PE(38:04)",
        "adduct": "[M+2Na-H]+",
        "mz": 812.519,
        "ccs": 284.96
    },
    {
        "name": "PE(38:05)",
        "adduct": "[M+2Na-H]+",
        "mz": 810.5023,
        "ccs": 283.55
    },
    {
        "name": "PE(38:06)",
        "adduct": "[M+2Na-H]+",
        "mz": 808.4859,
        "ccs": 281.0
    },
    {
        "name": "PE(39:02)",
        "adduct": "[M+2Na-H]+",
        "mz": 830.5643,
        "ccs": 291.84
    },
    {
        "name": "PE(40:05)",
        "adduct": "[M+2Na-H]+",
        "mz": 838.5306,
        "ccs": 289.53
    },
    {
        "name": "PE(40:06)",
        "adduct": "[M+2Na-H]+",
        "mz": 836.5146,
        "ccs": 287.86
    },
    {
        "name": "PE(40:07)",
        "adduct": "[M+2Na-H]+",
        "mz": 834.5003,
        "ccs": 286.07
    },
    {
        "name": "PE(34:01)",
        "adduct": "[M-H]-",
        "mz": 716.5274,
        "ccs": 266.91
    },
    {
        "name": "PE(34:02)",
        "adduct": "[M-H]-",
        "mz": 714.5113,
        "ccs": 265.55
    },
    {
        "name": "PE(34:03)",
        "adduct": "[M-H]-",
        "mz": 712.4947,
        "ccs": 263.76
    },
    {
        "name": "PE(36:00)",
        "adduct": "[M-H]-",
        "mz": 746.563,
        "ccs": 274.96
    },
    {
        "name": "PE(36:01)",
        "adduct": "[M-H]-",
        "mz": 744.5554,
        "ccs": 273.62
    },
    {
        "name": "PE(36:02)",
        "adduct": "[M-H]-",
        "mz": 742.5418,
        "ccs": 272.07
    },
    {
        "name": "PE(36:03)",
        "adduct": "[M-H]-",
        "mz": 740.5269,
        "ccs": 269.84
    },
    {
        "name": "PE(36:04)",
        "adduct": "[M-H]-",
        "mz": 738.5102,
        "ccs": 269.7
    },
    {
        "name": "PE(38:03)",
        "adduct": "[M-H]-",
        "mz": 768.5501,
        "ccs": 277.01
    },
    {
        "name": "PE(38:04)",
        "adduct": "[M-H]-",
        "mz": 766.543,
        "ccs": 276.04
    },
    {
        "name": "PE(38:05)",
        "adduct": "[M-H]-",
        "mz": 764.5257,
        "ccs": 274.82
    },
    {
        "name": "PE(38:06)",
        "adduct": "[M-H]-",
        "mz": 762.5117,
        "ccs": 273.81
    },
    {
        "name": "PE(40:05)",
        "adduct": "[M-H]-",
        "mz": 792.5544,
        "ccs": 280.89
    },
    {
        "name": "PE(40:06)",
        "adduct": "[M-H]-",
        "mz": 790.5417,
        "ccs": 280.5
    },
    {
        "name": "PC(32:00)",
        "adduct": "[M+H]+",
        "mz": 734.5658,
        "ccs": 278.4
    },
    {
        "name": "PC(32:01)",
        "adduct": "[M+H]+",
        "mz": 732.5529,
        "ccs": 276.5
    },
    {
        "name": "PC(34:01)",
        "adduct": "[M+H]+",
        "mz": 760.5846,
        "ccs": 281.97
    },
    {
        "name": "PC(34:02)",
        "adduct": "[M+H]+",
        "mz": 758.5682,
        "ccs": 279.51
    },
    {
        "name": "PC(34:03)",
        "adduct": "[M+H]+",
        "mz": 756.5518,
        "ccs": 277.12
    },
    {
        "name": "PC(35:01)",
        "adduct": "[M+H]+",
        "mz": 774.599,
        "ccs": 284.63
    },
    {
        "name": "PC(36:01)",
        "adduct": "[M+H]+",
        "mz": 788.6138,
        "ccs": 288.22
    },
    {
        "name": "PC(36:02)",
        "adduct": "[M+H]+",
        "mz": 786.5989,
        "ccs": 285.92
    },
    {
        "name": "PC(32:00)",
        "adduct": "[M+Na]+",
        "mz": 756.546,
        "ccs": 280.56
    },
    {
        "name": "PC(32:01)",
        "adduct": "[M+Na]+",
        "mz": 754.5314,
        "ccs": 279.16
    },
    {
        "name": "PC(32:02)",
        "adduct": "[M+Na]+",
        "mz": 752.5219,
        "ccs": 276.86
    },
    {
        "name": "PC(34:01)",
        "adduct": "[M+Na]+",
        "mz": 782.5639,
        "ccs": 284.83
    },
    {
        "name": "PC(34:02)",
        "adduct": "[M+Na]+",
        "mz": 780.5481,
        "ccs": 283.1
    },
    {
        "name": "PC(34:03)",
        "adduct": "[M+Na]+",
        "mz": 778.5284,
        "ccs": 281.98
    },
    {
        "name": "PC(35:01)",
        "adduct": "[M+Na]+",
        "mz": 796.58,
        "ccs": 287.14
    },
    {
        "name": "PC(35:02)",
        "adduct": "[M+Na]+",
        "mz": 794.5597,
        "ccs": 285.81
    },
    {
        "name": "PC(36:01)",
        "adduct": "[M+Na]+",
        "mz": 810.5932,
        "ccs": 290.25
    },
    {
        "name": "PC(36:02)",
        "adduct": "[M+Na]+",
        "mz": 808.5788,
        "ccs": 288.63
    },
    {
        "name": "PC(36:03)",
        "adduct": "[M+Na]+",
        "mz": 806.5616,
        "ccs": 287.02
    },
    {
        "name": "PC(36:04)",
        "adduct": "[M+Na]+",
        "mz": 804.5487,
        "ccs": 285.05
    },
    {
        "name": "PC(38:03)",
        "adduct": "[M+Na]+",
        "mz": 834.5955,
        "ccs": 293.06
    },
    {
        "name": "PC(40:04)",
        "adduct": "[M+Na]+",
        "mz": 860.607,
        "ccs": 297.42
    },
    {
        "name": "PC(40:05)",
        "adduct": "[M+Na]+",
        "mz": 858.5934,
        "ccs": 295.77
    },
    {
        "name": "PC(40:06)",
        "adduct": "[M+Na]+",
        "mz": 856.5786,
        "ccs": 294.42
    },
    {
        "name": "PC(34:01)",
        "adduct": "[M+K]+",
        "mz": 798.5409,
        "ccs": 285.76
    },
    {
        "name": "PC(34:02)",
        "adduct": "[M+K]+",
        "mz": 796.5292,
        "ccs": 283.28
    },
    {
        "name": "PC(36:01)",
        "adduct": "[M+K]+",
        "mz": 826.5677,
        "ccs": 291.07
    },
    {
        "name": "PC(36:02)",
        "adduct": "[M+K]+",
        "mz": 824.5561,
        "ccs": 289.17
    },
    {
        "name": "PC(34:00)",
        "adduct": "[M+2Na-H]+",
        "mz": 806.5644,
        "ccs": 286.12
    },
    {
        "name": "PC(34:01)",
        "adduct": "[M+2Na-H]+",
        "mz": 804.548,
        "ccs": 283.9
    },
    {
        "name": "PC(36:01)",
        "adduct": "[M+2Na-H]+",
        "mz": 832.5778,
        "ccs": 292.02
    },
    {
        "name": "PC(36:02)",
        "adduct": "[M+2Na-H]+",
        "mz": 830.5607,
        "ccs": 290.39
    },
    {
        "name": "PC(36:03)",
        "adduct": "[M+2Na-H]+",
        "mz": 828.5472,
        "ccs": 288.51
    },
    {
        "name": "PC(34:01)",
        "adduct": "[M+Cl]-",
        "mz": 794.5487,
        "ccs": 290.47
    },
    {
        "name": "PC(34:02)",
        "adduct": "[M+Cl]-",
        "mz": 792.5358,
        "ccs": 289.37
    },
    {
        "name": "PC(34:03)",
        "adduct": "[M+Cl]-",
        "mz": 790.5202,
        "ccs": 287.96
    },
    {
        "name": "PC(36:01)",
        "adduct": "[M+Cl]-",
        "mz": 822.576,
        "ccs": 296.27
    },
    {
        "name": "PC(36:02)",
        "adduct": "[M+Cl]-",
        "mz": 820.5635,
        "ccs": 295.12
    },
    {
        "name": "PC(36:03)",
        "adduct": "[M+Cl]-",
        "mz": 818.552,
        "ccs": 293.42
    },
    {
        "name": "PC(36:04)",
        "adduct": "[M+Cl]-",
        "mz": 816.538,
        "ccs": 293.08
    },
    {
        "name": "PC(38:02)",
        "adduct": "[M+Cl]-",
        "mz": 848.602,
        "ccs": 300.55
    },
    {
        "name": "PC(38:03)",
        "adduct": "[M+Cl]-",
        "mz": 846.5833,
        "ccs": 299.51
    },
    {
        "name": "PC(38:04)",
        "adduct": "[M+Cl]-",
        "mz": 844.5647,
        "ccs": 298.46
    },
    {
        "name": "PC(38:05)",
        "adduct": "[M+Cl]-",
        "mz": 842.5458,
        "ccs": 297.1
    },
    {
        "name": "PC(38:06)",
        "adduct": "[M+Cl]-",
        "mz": 840.535,
        "ccs": 296.13
    },
    {
        "name": "PC(32:00)",
        "adduct": "[M+HCOO]-",
        "mz": 778.5618,
        "ccs": 286.82
    },
    {
        "name": "PC(32:01)",
        "adduct": "[M+HCOO]-",
        "mz": 776.5479,
        "ccs": 284.71
    },
    {
        "name": "PC(34:01)",
        "adduct": "[M+HCOO]-",
        "mz": 804.5784,
        "ccs": 290.79
    },
    {
        "name": "PC(34:02)",
        "adduct": "[M+HCOO]-",
        "mz": 802.5641,
        "ccs": 289.31
    },
    {
        "name": "PC(34:03)",
        "adduct": "[M+HCOO]-",
        "mz": 800.5477,
        "ccs": 288.8
    },
    {
        "name": "PC(36:01)",
        "adduct": "[M+HCOO]-",
        "mz": 832.6107,
        "ccs": 296.46
    },
    {
        "name": "PC(36:02)",
        "adduct": "[M+HCOO]-",
        "mz": 830.5951,
        "ccs": 295.45
    },
    {
        "name": "PC(36:03)",
        "adduct": "[M+HCOO]-",
        "mz": 828.5774,
        "ccs": 293.56
    },
    {
        "name": "PC(36:04)",
        "adduct": "[M+HCOO]-",
        "mz": 826.5649,
        "ccs": 292.86
    },
    {
        "name": "PC(38:04)",
        "adduct": "[M+HCOO]-",
        "mz": 854.593,
        "ccs": 298.03
    },
    {
        "name": "PC(38:05)",
        "adduct": "[M+HCOO]-",
        "mz": 852.5791,
        "ccs": 297.3
    },
    {
        "name": "PC(38:06)",
        "adduct": "[M+HCOO]-",
        "mz": 850.5669,
        "ccs": 295.99
    },
    {
        "name": "PS(36:01)",
        "adduct": "[M+H]+",
        "mz": 790.561,
        "ccs": 283.39
    },
    {
        "name": "PS(36:02)",
        "adduct": "[M+H]+",
        "mz": 788.5447,
        "ccs": 280.92
    },
    {
        "name": "PS(38:01)",
        "adduct": "[M+H]+",
        "mz": 818.5903,
        "ccs": 289.63
    },
    {
        "name": "PS(38:02)",
        "adduct": "[M+H]+",
        "mz": 816.5749,
        "ccs": 287.73
    },
    {
        "name": "PS(38:04)",
        "adduct": "[M+H]+",
        "mz": 812.5434,
        "ccs": 284.44
    },
    {
        "name": "PS(38:05)",
        "adduct": "[M+H]+",
        "mz": 810.5276,
        "ccs": 281.67
    },
    {
        "name": "PS(40:01)",
        "adduct": "[M+H]+",
        "mz": 846.6197,
        "ccs": 295.93
    },
    {
        "name": "PS(40:02)",
        "adduct": "[M+H]+",
        "mz": 844.606,
        "ccs": 294.02
    },
    {
        "name": "PS(40:03)",
        "adduct": "[M+H]+",
        "mz": 842.588,
        "ccs": 292.62
    },
    {
        "name": "PS(40:04)",
        "adduct": "[M+H]+",
        "mz": 840.5746,
        "ccs": 291.15
    },
    {
        "name": "PS(40:05)",
        "adduct": "[M+H]+",
        "mz": 838.5585,
        "ccs": 289.6
    },
    {
        "name": "PS(40:06)",
        "adduct": "[M+H]+",
        "mz": 836.5454,
        "ccs": 287.73
    },
    {
        "name": "PS(42:01)",
        "adduct": "[M+H]+",
        "mz": 874.6509,
        "ccs": 301.86
    },
    {
        "name": "PS(42:02)",
        "adduct": "[M+H]+",
        "mz": 872.6375,
        "ccs": 299.5
    },
    {
        "name": "PS(42:03)",
        "adduct": "[M+H]+",
        "mz": 870.6192,
        "ccs": 298.03
    },
    {
        "name": "PS(42:04)",
        "adduct": "[M+H]+",
        "mz": 868.6053,
        "ccs": 296.39
    },
    {
        "name": "PS(42:05)",
        "adduct": "[M+H]+",
        "mz": 866.5897,
        "ccs": 295.24
    },
    {
        "name": "PS(40:03)",
        "adduct": "[M+Na]+",
        "mz": 864.5702,
        "ccs": 296.28
    },
    {
        "name": "PS(40:04)",
        "adduct": "[M+Na]+",
        "mz": 862.5564,
        "ccs": 295.22
    },
    {
        "name": "PS(40:05)",
        "adduct": "[M+Na]+",
        "mz": 860.5406,
        "ccs": 293.82
    },
    {
        "name": "PS(40:06)",
        "adduct": "[M+Na]+",
        "mz": 858.5271,
        "ccs": 291.7
    },
    {
        "name": "PS(40:07)",
        "adduct": "[M+Na]+",
        "mz": 856.5086,
        "ccs": 289.65
    },
    {
        "name": "PS(42:01)",
        "adduct": "[M+Na]+",
        "mz": 896.6328,
        "ccs": 303.25
    },
    {
        "name": "PS(42:02)",
        "adduct": "[M+Na]+",
        "mz": 894.6164,
        "ccs": 302.0
    },
    {
        "name": "PS(42:04)",
        "adduct": "[M+Na]+",
        "mz": 890.5872,
        "ccs": 298.86
    },
    {
        "name": "PS(42:05)",
        "adduct": "[M+Na]+",
        "mz": 888.5715,
        "ccs": 297.67
    },
    {
        "name": "PS(44:10)",
        "adduct": "[M+Na]+",
        "mz": 906.525,
        "ccs": 296.88
    },
    {
        "name": "PS(36:01)",
        "adduct": "[M+K]+",
        "mz": 828.5129,
        "ccs": 287.48
    },
    {
        "name": "PS(36:02)",
        "adduct": "[M+K]+",
        "mz": 826.4998,
        "ccs": 285.23
    },
    {
        "name": "PS(38:04)",
        "adduct": "[M+K]+",
        "mz": 850.4972,
        "ccs": 289.37
    },
    {
        "name": "PS(38:05)",
        "adduct": "[M+K]+",
        "mz": 848.4824,
        "ccs": 286.6
    },
    {
        "name": "PS(40:04)",
        "adduct": "[M+K]+",
        "mz": 878.5268,
        "ccs": 295.44
    },
    {
        "name": "PS(40:05)",
        "adduct": "[M+K]+",
        "mz": 876.5115,
        "ccs": 294.22
    },
    {
        "name": "PS(40:06)",
        "adduct": "[M+K]+",
        "mz": 874.499,
        "ccs": 292.76
    },
    {
        "name": "PS(42:09)",
        "adduct": "[M+K]+",
        "mz": 896.4798,
        "ccs": 294.57
    },
    {
        "name": "PS(34:01)",
        "adduct": "[M+2Na-H]+",
        "mz": 806.4916,
        "ccs": 280.81
    },
    {
        "name": "PS(36:01)",
        "adduct": "[M+2Na-H]+",
        "mz": 834.5246,
        "ccs": 287.95
    },
    {
        "name": "PS(36:02)",
        "adduct": "[M+2Na-H]+",
        "mz": 832.5078,
        "ccs": 285.97
    },
    {
        "name": "PS(36:04)",
        "adduct": "[M+2Na-H]+",
        "mz": 828.4739,
        "ccs": 281.53
    },
    {
        "name": "PS(37:01)",
        "adduct": "[M+2Na-H]+",
        "mz": 848.5383,
        "ccs": 293.47
    },
    {
        "name": "PS(37:02)",
        "adduct": "[M+2Na-H]+",
        "mz": 846.5244,
        "ccs": 289.29
    },
    {
        "name": "PS(37:04)",
        "adduct": "[M+2Na-H]+",
        "mz": 842.4921,
        "ccs": 285.85
    },
    {
        "name": "PS(38:01)",
        "adduct": "[M+2Na-H]+",
        "mz": 862.5536,
        "ccs": 295.38
    },
    {
        "name": "PS(38:02)",
        "adduct": "[M+2Na-H]+",
        "mz": 860.5381,
        "ccs": 292.46
    },
    {
        "name": "PS(38:04)",
        "adduct": "[M+2Na-H]+",
        "mz": 856.5075,
        "ccs": 288.75
    },
    {
        "name": "PS(38:05)",
        "adduct": "[M+2Na-H]+",
        "mz": 854.4905,
        "ccs": 285.68
    },
    {
        "name": "PS(39:04)",
        "adduct": "[M+2Na-H]+",
        "mz": 870.5224,
        "ccs": 291.95
    },
    {
        "name": "PS(40:01)",
        "adduct": "[M+2Na-H]+",
        "mz": 890.5819,
        "ccs": 301.13
    },
    {
        "name": "PS(40:02)",
        "adduct": "[M+2Na-H]+",
        "mz": 888.5683,
        "ccs": 299.44
    },
    {
        "name": "PS(40:04)",
        "adduct": "[M+2Na-H]+",
        "mz": 884.5388,
        "ccs": 298.27
    },
    {
        "name": "PS(40:05)",
        "adduct": "[M+2Na-H]+",
        "mz": 882.523,
        "ccs": 297.17
    },
    {
        "name": "PS(40:06)",
        "adduct": "[M+2Na-H]+",
        "mz": 880.5083,
        "ccs": 295.61
    },
    {
        "name": "PS(40:07)",
        "adduct": "[M+2Na-H]+",
        "mz": 878.4907,
        "ccs": 290.15
    },
    {
        "name": "PS(40:08)",
        "adduct": "[M+2Na-H]+",
        "mz": 876.4755,
        "ccs": 287.97
    },
    {
        "name": "PS(40:09)",
        "adduct": "[M+2Na-H]+",
        "mz": 874.4608,
        "ccs": 284.82
    },
    {
        "name": "PS(41:05)",
        "adduct": "[M+2Na-H]+",
        "mz": 896.537,
        "ccs": 298.43
    },
    {
        "name": "PS(41:06)",
        "adduct": "[M+2Na-H]+",
        "mz": 894.5234,
        "ccs": 296.18
    },
    {
        "name": "PS(42:02)",
        "adduct": "[M+2Na-H]+",
        "mz": 916.6024,
        "ccs": 306.07
    },
    {
        "name": "PS(42:04)",
        "adduct": "[M+2Na-H]+",
        "mz": 912.5685,
        "ccs": 304.19
    },
    {
        "name": "PS(42:05)",
        "adduct": "[M+2Na-H]+",
        "mz": 910.5531,
        "ccs": 300.15
    },
    {
        "name": "PS(42:06)",
        "adduct": "[M+2Na-H]+",
        "mz": 908.5354,
        "ccs": 297.48
    },
    {
        "name": "PS(42:07)",
        "adduct": "[M+2Na-H]+",
        "mz": 906.5225,
        "ccs": 296.35
    },
    {
        "name": "PS(42:08)",
        "adduct": "[M+2Na-H]+",
        "mz": 904.5064,
        "ccs": 295.25
    },
    {
        "name": "PS(42:09)",
        "adduct": "[M+2Na-H]+",
        "mz": 902.4924,
        "ccs": 292.63
    },
    {
        "name": "PS(44:05)",
        "adduct": "[M+2Na-H]+",
        "mz": 938.5842,
        "ccs": 306.87
    },
    {
        "name": "PS(44:07)",
        "adduct": "[M+2Na-H]+",
        "mz": 934.5528,
        "ccs": 303.11
    },
    {
        "name": "PS(44:08)",
        "adduct": "[M+2Na-H]+",
        "mz": 932.5362,
        "ccs": 301.25
    },
    {
        "name": "PS(36:00)",
        "adduct": "[M-H]-",
        "mz": 790.5539,
        "ccs": 284.03
    },
    {
        "name": "PS(36:01)",
        "adduct": "[M-H]-",
        "mz": 788.5477,
        "ccs": 282.92
    },
    {
        "name": "PS(36:02)",
        "adduct": "[M-H]-",
        "mz": 786.5325,
        "ccs": 281.82
    },
    {
        "name": "PS(38:02)",
        "adduct": "[M-H]-",
        "mz": 814.5598,
        "ccs": 287.56
    },
    {
        "name": "PS(38:03)",
        "adduct": "[M-H]-",
        "mz": 812.5444,
        "ccs": 286.53
    },
    {
        "name": "PS(38:04)",
        "adduct": "[M-H]-",
        "mz": 810.5303,
        "ccs": 285.11
    },
    {
        "name": "PS(38:05)",
        "adduct": "[M-H]-",
        "mz": 808.5139,
        "ccs": 283.69
    },
    {
        "name": "PS(40:04)",
        "adduct": "[M-H]-",
        "mz": 838.5602,
        "ccs": 291.3
    },
    {
        "name": "PS(40:05)",
        "adduct": "[M-H]-",
        "mz": 836.5461,
        "ccs": 290.27
    },
    {
        "name": "PS(40:06)",
        "adduct": "[M-H]-",
        "mz": 834.5323,
        "ccs": 289.09
    },
    {
        "name": "PS(40:07)",
        "adduct": "[M-H]-",
        "mz": 832.5163,
        "ccs": 287.37
    },
    {
        "name": "PS(42:08)",
        "adduct": "[M-H]-",
        "mz": 858.5239,
        "ccs": 291.98
    },
    {
        "name": "PS(42:09)",
        "adduct": "[M-H]-",
        "mz": 856.5124,
        "ccs": 290.63
    },
    {
        "name": "SM(34:01)",
        "adduct": "[M+H]+",
        "mz": 703.5759,
        "ccs": 280.06
    },
    {
        "name": "SM(36:01)",
        "adduct": "[M+H]+",
        "mz": 731.6091,
        "ccs": 286.24
    },
    {
        "name": "SM(36:02)",
        "adduct": "[M+H]+",
        "mz": 729.5916,
        "ccs": 284.15
    },
    {
        "name": "SM(37:01)",
        "adduct": "[M+H]+",
        "mz": 745.6237,
        "ccs": 288.67
    },
    {
        "name": "SM(38:01)",
        "adduct": "[M+H]+",
        "mz": 759.6387,
        "ccs": 292.26
    },
    {
        "name": "SM(39:01)",
        "adduct": "[M+H]+",
        "mz": 773.6558,
        "ccs": 295.85
    },
    {
        "name": "SM(40:00)",
        "adduct": "[M+H]+",
        "mz": 789.6839,
        "ccs": 299.61
    },
    {
        "name": "SM(40:01)",
        "adduct": "[M+H]+",
        "mz": 787.67,
        "ccs": 297.88
    },
    {
        "name": "SM(40:02)",
        "adduct": "[M+H]+",
        "mz": 785.6547,
        "ccs": 295.66
    },
    {
        "name": "SM(41:00)",
        "adduct": "[M+H]+",
        "mz": 803.6977,
        "ccs": 302.29
    },
    {
        "name": "SM(41:01)",
        "adduct": "[M+H]+",
        "mz": 801.6853,
        "ccs": 301.14
    },
    {
        "name": "SM(41:02)",
        "adduct": "[M+H]+",
        "mz": 799.6693,
        "ccs": 298.91
    },
    {
        "name": "SM(42:00)",
        "adduct": "[M+H]+",
        "mz": 817.7162,
        "ccs": 305.33
    },
    {
        "name": "SM(42:01)",
        "adduct": "[M+H]+",
        "mz": 815.7001,
        "ccs": 303.17
    },
    {
        "name": "SM(42:02)",
        "adduct": "[M+H]+",
        "mz": 813.6862,
        "ccs": 301.43
    },
    {
        "name": "SM(42:03)",
        "adduct": "[M+H]+",
        "mz": 811.6685,
        "ccs": 299.58
    },
    {
        "name": "SM(42:04)",
        "adduct": "[M+H]+",
        "mz": 809.6517,
        "ccs": 297.81
    },
    {
        "name": "SM(43:01)",
        "adduct": "[M+H]+",
        "mz": 829.7152,
        "ccs": 306.91
    },
    {
        "name": "SM(43:02)",
        "adduct": "[M+H]+",
        "mz": 827.701,
        "ccs": 304.47
    },
    {
        "name": "SM(44:01)",
        "adduct": "[M+H]+",
        "mz": 843.7293,
        "ccs": 309.76
    },
    {
        "name": "SM(44:02)",
        "adduct": "[M+H]+",
        "mz": 841.7192,
        "ccs": 307.52
    },
    {
        "name": "SM(36:01)",
        "adduct": "[M+Na-H2O]+",
        "mz": 735.5771,
        "ccs": 280.09
    },
    {
        "name": "SM(42:02)",
        "adduct": "[M+Na-H2O]+",
        "mz": 817.6553,
        "ccs": 301.19
    },
    {
        "name": "SM(34:01)",
        "adduct": "[M+Na]+",
        "mz": 725.5557,
        "ccs": 278.77
    },
    {
        "name": "SM(35:01)",
        "adduct": "[M+Na]+",
        "mz": 739.5711,
        "ccs": 280.61
    },
    {
        "name": "SM(36:01)",
        "adduct": "[M+Na]+",
        "mz": 753.5909,
        "ccs": 285.86
    },
    {
        "name": "SM(36:02)",
        "adduct": "[M+Na]+",
        "mz": 751.5745,
        "ccs": 280.32
    },
    {
        "name": "SM(37:01)",
        "adduct": "[M+Na]+",
        "mz": 767.6031,
        "ccs": 285.35
    },
    {
        "name": "SM(38:01)",
        "adduct": "[M+Na]+",
        "mz": 781.6198,
        "ccs": 292.18
    },
    {
        "name": "SM(39:01)",
        "adduct": "[M+Na]+",
        "mz": 795.6371,
        "ccs": 294.58
    },
    {
        "name": "SM(40:01)",
        "adduct": "[M+Na]+",
        "mz": 809.6505,
        "ccs": 296.0
    },
    {
        "name": "SM(40:02)",
        "adduct": "[M+Na]+",
        "mz": 807.6352,
        "ccs": 292.53
    },
    {
        "name": "SM(41:01)",
        "adduct": "[M+Na]+",
        "mz": 823.6652,
        "ccs": 299.31
    },
    {
        "name": "SM(41:02)",
        "adduct": "[M+Na]+",
        "mz": 821.6499,
        "ccs": 296.38
    },
    {
        "name": "SM(42:01)",
        "adduct": "[M+Na]+",
        "mz": 837.6793,
        "ccs": 302.6
    },
    {
        "name": "SM(42:02)",
        "adduct": "[M+Na]+",
        "mz": 835.668,
        "ccs": 300.53
    },
    {
        "name": "SM(42:03)",
        "adduct": "[M+Na]+",
        "mz": 833.6517,
        "ccs": 297.59
    },
    {
        "name": "SM(43:01)",
        "adduct": "[M+Na]+",
        "mz": 851.6933,
        "ccs": 304.16
    },
    {
        "name": "SM(43:02)",
        "adduct": "[M+Na]+",
        "mz": 849.6813,
        "ccs": 303.6
    },
    {
        "name": "SM(44:01)",
        "adduct": "[M+Na]+",
        "mz": 865.7093,
        "ccs": 307.86
    },
    {
        "name": "SM(44:02)",
        "adduct": "[M+Na]+",
        "mz": 863.6969,
        "ccs": 306.5
    },
    {
        "name": "SM(44:03)",
        "adduct": "[M+Na]+",
        "mz": 861.6823,
        "ccs": 304.66
    },
    {
        "name": "SM(36:01)",
        "adduct": "[M+K]+",
        "mz": 769.5636,
        "ccs": 288.38
    },
    {
        "name": "SM(38:00)",
        "adduct": "[M+2Na-H]+",
        "mz": 805.6204,
        "ccs": 294.68
    },
    {
        "name": "SM(41:00)",
        "adduct": "[M+2Na-H]+",
        "mz": 847.6631,
        "ccs": 301.12
    },
    {
        "name": "SM(34:01)",
        "adduct": "[M+Cl]-",
        "mz": 737.5404,
        "ccs": 284.26
    },
    {
        "name": "SM(36:01)",
        "adduct": "[M+Cl]-",
        "mz": 765.5717,
        "ccs": 288.69
    },
    {
        "name": "SM(38:01)",
        "adduct": "[M+Cl]-",
        "mz": 793.6024,
        "ccs": 294.7
    },
    {
        "name": "SM(40:00)",
        "adduct": "[M+Cl]-",
        "mz": 823.6424,
        "ccs": 301.5
    },
    {
        "name": "SM(40:01)",
        "adduct": "[M+Cl]-",
        "mz": 821.6331,
        "ccs": 300.79
    },
    {
        "name": "SM(40:02)",
        "adduct": "[M+Cl]-",
        "mz": 819.622,
        "ccs": 299.55
    },
    {
        "name": "SM(42:01)",
        "adduct": "[M+Cl]-",
        "mz": 849.6602,
        "ccs": 305.77
    },
    {
        "name": "SM(42:02)",
        "adduct": "[M+Cl]-",
        "mz": 847.6522,
        "ccs": 304.71
    },
    {
        "name": "SM(34:01)",
        "adduct": "[M+HCOO]-",
        "mz": 747.5688,
        "ccs": 284.66
    },
    {
        "name": "SM(36:01)",
        "adduct": "[M+HCOO]-",
        "mz": 775.6009,
        "ccs": 290.34
    },
    {
        "name": "SM(36:02)",
        "adduct": "[M+HCOO]-",
        "mz": 773.5819,
        "ccs": 289.73
    },
    {
        "name": "SM(38:01)",
        "adduct": "[M+HCOO]-",
        "mz": 803.6324,
        "ccs": 296.3
    },
    {
        "name": "SM(40:00)",
        "adduct": "[M+HCOO]-",
        "mz": 833.6721,
        "ccs": 303.38
    },
    {
        "name": "SM(40:01)",
        "adduct": "[M+HCOO]-",
        "mz": 831.6622,
        "ccs": 301.44
    },
    {
        "name": "SM(40:02)",
        "adduct": "[M+HCOO]-",
        "mz": 829.6453,
        "ccs": 299.75
    },
    {
        "name": "SM(41:02)",
        "adduct": "[M+HCOO]-",
        "mz": 843.656,
        "ccs": 303.33
    },
    {
        "name": "SM(42:00)",
        "adduct": "[M+HCOO]-",
        "mz": 861.7037,
        "ccs": 308.73
    },
    {
        "name": "SM(42:01)",
        "adduct": "[M+HCOO]-",
        "mz": 859.6912,
        "ccs": 306.96
    },
    {
        "name": "SM(42:02)",
        "adduct": "[M+HCOO]-",
        "mz": 857.6788,
        "ccs": 305.63
    },
    {
        "name": "SM(42:03)",
        "adduct": "[M+HCOO]-",
        "mz": 855.663,
        "ccs": 304.85
    },
    {
        "name": "GlcCer(47:03)",
        "adduct": "[M+H-2H2O]+",
        "mz": 842.7211,
        "ccs": 307.66
    },
    {
        "name": "GlcCer(50:04)",
        "adduct": "[M+H-2H2O]+",
        "mz": 882.7547,
        "ccs": 314.25
    },
    {
        "name": "GlcCer(36:01)",
        "adduct": "[M+H-H2O]+",
        "mz": 710.5945,
        "ccs": 279.86
    },
    {
        "name": "GlcCer(38:01)",
        "adduct": "[M+H-H2O]+",
        "mz": 738.6254,
        "ccs": 286.62
    },
    {
        "name": "GlcCer(40:01)",
        "adduct": "[M+H-H2O]+",
        "mz": 766.6566,
        "ccs": 292.77
    },
    {
        "name": "GlcCer(40:02)",
        "adduct": "[M+H-H2O]+",
        "mz": 764.64,
        "ccs": 290.36
    },
    {
        "name": "GlcCer(41:01)",
        "adduct": "[M+H-H2O]+",
        "mz": 780.6728,
        "ccs": 294.63
    },
    {
        "name": "GlcCer(42:01)",
        "adduct": "[M+H-H2O]+",
        "mz": 794.6867,
        "ccs": 298.36
    },
    {
        "name": "GlcCer(42:02)",
        "adduct": "[M+H-H2O]+",
        "mz": 792.673,
        "ccs": 296.4
    },
    {
        "name": "GlcCer(44:02)",
        "adduct": "[M+H-H2O]+",
        "mz": 820.7016,
        "ccs": 301.46
    },
    {
        "name": "GlcCer(46:01)",
        "adduct": "[M+H-H2O]+",
        "mz": 886.7493,
        "ccs": 316.22
    },
    {
        "name": "GlcCer(46:02)",
        "adduct": "[M+H-H2O]+",
        "mz": 884.7344,
        "ccs": 314.3
    },
    {
        "name": "GlcCer(47:00)",
        "adduct": "[M+Na-2H2O]+",
        "mz": 870.7504,
        "ccs": 313.61
    },
    {
        "name": "GlcCer(49:00)",
        "adduct": "[M+Na-2H2O]+",
        "mz": 898.7789,
        "ccs": 318.7
    },
    {
        "name": "GlcCer(49:01)",
        "adduct": "[M+Na-2H2O]+",
        "mz": 896.7674,
        "ccs": 317.53
    },
    {
        "name": "GlcCer(36:00)",
        "adduct": "[M+H]+",
        "mz": 730.6192,
        "ccs": 284.59
    },
    {
        "name": "GlcCer(36:01)",
        "adduct": "[M+H]+",
        "mz": 728.6059,
        "ccs": 282.43
    },
    {
        "name": "GlcCer(36:02)",
        "adduct": "[M+H]+",
        "mz": 726.5888,
        "ccs": 281.37
    },
    {
        "name": "GlcCer(38:00)",
        "adduct": "[M+H]+",
        "mz": 758.6497,
        "ccs": 290.18
    },
    {
        "name": "GlcCer(38:01)",
        "adduct": "[M+H]+",
        "mz": 756.6355,
        "ccs": 288.15
    },
    {
        "name": "GlcCer(38:02)",
        "adduct": "[M+H]+",
        "mz": 754.6199,
        "ccs": 287.87
    },
    {
        "name": "GlcCer(38:03)",
        "adduct": "[M+H]+",
        "mz": 752.601,
        "ccs": 284.43
    },
    {
        "name": "GlcCer(40:00)",
        "adduct": "[M+H]+",
        "mz": 786.682,
        "ccs": 296.24
    },
    {
        "name": "GlcCer(40:01)",
        "adduct": "[M+H]+",
        "mz": 784.6669,
        "ccs": 293.87
    },
    {
        "name": "GlcCer(40:02)",
        "adduct": "[M+H]+",
        "mz": 782.6531,
        "ccs": 293.98
    },
    {
        "name": "GlcCer(41:01)",
        "adduct": "[M+H]+",
        "mz": 798.6821,
        "ccs": 297.12
    },
    {
        "name": "GlcCer(42:00)",
        "adduct": "[M+H]+",
        "mz": 814.7116,
        "ccs": 302.3
    },
    {
        "name": "GlcCer(42:01)",
        "adduct": "[M+H]+",
        "mz": 812.6985,
        "ccs": 300.59
    },
    {
        "name": "GlcCer(42:02)",
        "adduct": "[M+H]+",
        "mz": 810.6847,
        "ccs": 299.26
    },
    {
        "name": "GlcCer(43:02)",
        "adduct": "[M+H]+",
        "mz": 824.6967,
        "ccs": 302.04
    },
    {
        "name": "GlcCer(44:01)",
        "adduct": "[M+H]+",
        "mz": 840.7251,
        "ccs": 306.44
    },
    {
        "name": "GlcCer(44:02)",
        "adduct": "[M+H]+",
        "mz": 838.7135,
        "ccs": 305.11
    },
    {
        "name": "GlcCer(34:00)",
        "adduct": "[M+Na]+",
        "mz": 724.5714,
        "ccs": 280.92
    },
    {
        "name": "GlcCer(34:01)",
        "adduct": "[M+Na]+",
        "mz": 722.5568,
        "ccs": 278.95
    },
    {
        "name": "GlcCer(36:01)",
        "adduct": "[M+Na]+",
        "mz": 750.5887,
        "ccs": 284.0
    },
    {
        "name": "GlcCer(36:02)",
        "adduct": "[M+Na]+",
        "mz": 748.5701,
        "ccs": 281.52
    },
    {
        "name": "GlcCer(37:01)",
        "adduct": "[M+Na]+",
        "mz": 764.6009,
        "ccs": 287.43
    },
    {
        "name": "GlcCer(38:00)",
        "adduct": "[M+Na]+",
        "mz": 780.6319,
        "ccs": 291.27
    },
    {
        "name": "GlcCer(38:01)",
        "adduct": "[M+Na]+",
        "mz": 778.6185,
        "ccs": 290.52
    },
    {
        "name": "GlcCer(38:02)",
        "adduct": "[M+Na]+",
        "mz": 776.6013,
        "ccs": 287.34
    },
    {
        "name": "GlcCer(39:01)",
        "adduct": "[M+Na]+",
        "mz": 792.6308,
        "ccs": 291.95
    },
    {
        "name": "GlcCer(40:00)",
        "adduct": "[M+Na]+",
        "mz": 808.6655,
        "ccs": 297.72
    },
    {
        "name": "GlcCer(40:01)",
        "adduct": "[M+Na]+",
        "mz": 806.6491,
        "ccs": 296.15
    },
    {
        "name": "GlcCer(40:02)",
        "adduct": "[M+Na]+",
        "mz": 804.634,
        "ccs": 292.09
    },
    {
        "name": "GlcCer(40:03)",
        "adduct": "[M+Na]+",
        "mz": 802.6156,
        "ccs": 290.28
    },
    {
        "name": "GlcCer(41:01)",
        "adduct": "[M+Na]+",
        "mz": 820.6629,
        "ccs": 297.42
    },
    {
        "name": "GlcCer(41:02)",
        "adduct": "[M+Na]+",
        "mz": 818.6491,
        "ccs": 296.1
    },
    {
        "name": "GlcCer(42:00)",
        "adduct": "[M+Na]+",
        "mz": 836.6944,
        "ccs": 303.14
    },
    {
        "name": "GlcCer(42:01)",
        "adduct": "[M+Na]+",
        "mz": 834.681,
        "ccs": 301.76
    },
    {
        "name": "GlcCer(42:02)",
        "adduct": "[M+Na]+",
        "mz": 832.6685,
        "ccs": 299.53
    },
    {
        "name": "GlcCer(42:03)",
        "adduct": "[M+Na]+",
        "mz": 830.6487,
        "ccs": 297.28
    },
    {
        "name": "GlcCer(43:02)",
        "adduct": "[M+Na]+",
        "mz": 846.6792,
        "ccs": 302.4
    },
    {
        "name": "GlcCer(43:03)",
        "adduct": "[M+Na]+",
        "mz": 844.6624,
        "ccs": 300.75
    },
    {
        "name": "GlcCer(44:01)",
        "adduct": "[M+Na]+",
        "mz": 862.7107,
        "ccs": 307.93
    },
    {
        "name": "GlcCer(44:02)",
        "adduct": "[M+Na]+",
        "mz": 860.6965,
        "ccs": 306.31
    },
    {
        "name": "GlcCer(44:03)",
        "adduct": "[M+Na]+",
        "mz": 858.6789,
        "ccs": 303.93
    },
    {
        "name": "GlcCer(36:01)",
        "adduct": "[M+Cl]-",
        "mz": 762.5696,
        "ccs": 284.18
    },
    {
        "name": "GlcCer(40:00)",
        "adduct": "[M+Cl]-",
        "mz": 820.6427,
        "ccs": 293.17
    },
    {
        "name": "GlcCer(40:01)",
        "adduct": "[M+Cl]-",
        "mz": 818.6299,
        "ccs": 292.56
    },
    {
        "name": "GlcCer(42:01)",
        "adduct": "[M+Cl]-",
        "mz": 846.6591,
        "ccs": 298.88
    },
    {
        "name": "GlcCer(42:02)",
        "adduct": "[M+Cl]-",
        "mz": 844.6497,
        "ccs": 298.77
    },
    {
        "name": "GlcCer(36:01)",
        "adduct": "[M+HCOO]-",
        "mz": 772.6004,
        "ccs": 287.29
    },
    {
        "name": "GlcCer(40:00)",
        "adduct": "[M+HCOO]-",
        "mz": 830.6766,
        "ccs": 298.07
    },
    {
        "name": "GlcCer(40:01)",
        "adduct": "[M+HCOO]-",
        "mz": 828.6816,
        "ccs": 298.16
    },
    {
        "name": "GlcCer(42:01)",
        "adduct": "[M+HCOO]-",
        "mz": 856.6896,
        "ccs": 302.85
    },
    {
        "name": "GlcCer(42:02)",
        "adduct": "[M+HCOO]-",
        "mz": 854.6779,
        "ccs": 301.95
    },
    {
        "name": "Cer(42:01)",
        "adduct": "[M+H-2H2O]+",
        "mz": 614.6218,
        "ccs": 273.88
    },
    {
        "name": "Cer(42:02)",
        "adduct": "[M+H-2H2O]+",
        "mz": 612.6086,
        "ccs": 271.35
    },
    {
        "name": "Cer(36:01)",
        "adduct": "[M+H-H2O]+",
        "mz": 548.5402,
        "ccs": 257.25
    },
    {
        "name": "Cer(38:01)",
        "adduct": "[M+H-H2O]+",
        "mz": 576.5715,
        "ccs": 263.93
    },
    {
        "name": "Cer(40:01)",
        "adduct": "[M+H-H2O]+",
        "mz": 604.6032,
        "ccs": 269.41
    },
    {
        "name": "Cer(40:02)",
        "adduct": "[M+H-H2O]+",
        "mz": 602.5888,
        "ccs": 267.47
    },
    {
        "name": "Cer(41:01)",
        "adduct": "[M+H-H2O]+",
        "mz": 618.617,
        "ccs": 272.16
    },
    {
        "name": "Cer(42:01)",
        "adduct": "[M+H-H2O]+",
        "mz": 632.6333,
        "ccs": 275.06
    },
    {
        "name": "Cer(42:02)",
        "adduct": "[M+H-H2O]+",
        "mz": 630.6199,
        "ccs": 273.26
    },
    {
        "name": "Cer(42:03)",
        "adduct": "[M+H-H2O]+",
        "mz": 628.6034,
        "ccs": 271.44
    },
    {
        "name": "Cer(43:02)",
        "adduct": "[M+H-H2O]+",
        "mz": 644.6348,
        "ccs": 275.52
    },
    {
        "name": "Cer(44:02)",
        "adduct": "[M+H-H2O]+",
        "mz": 658.6489,
        "ccs": 279.7
    },
    {
        "name": "Cer(36:00)",
        "adduct": "[M+H]+",
        "mz": 568.5673,
        "ccs": 261.92
    },
    {
        "name": "Cer(38:00)",
        "adduct": "[M+H]+",
        "mz": 596.597,
        "ccs": 267.37
    },
    {
        "name": "Cer(40:00)",
        "adduct": "[M+H]+",
        "mz": 624.6294,
        "ccs": 274.03
    },
    {
        "name": "Cer(40:02)",
        "adduct": "[M+H]+",
        "mz": 620.5999,
        "ccs": 272.27
    },
    {
        "name": "Cer(42:00)",
        "adduct": "[M+H]+",
        "mz": 652.6597,
        "ccs": 280.05
    },
    {
        "name": "Cer(42:01)",
        "adduct": "[M+H]+",
        "mz": 650.6451,
        "ccs": 277.56
    },
    {
        "name": "Cer(42:02)",
        "adduct": "[M+H]+",
        "mz": 648.6289,
        "ccs": 276.77
    },
    {
        "name": "Cer(42:03)",
        "adduct": "[M+H]+",
        "mz": 646.615,
        "ccs": 275.18
    },
    {
        "name": "Cer(42:00)",
        "adduct": "[M+Na]+",
        "mz": 674.6457,
        "ccs": 281.85
    },
    {
        "name": "PE(o36:01)",
        "adduct": "[M+H]+",
        "mz": 732.5885,
        "ccs": 277.08
    },
    {
        "name": "PE(o36:02)",
        "adduct": "[M+H]+",
        "mz": 730.5725,
        "ccs": 274.98
    },
    {
        "name": "PE(o36:03)",
        "adduct": "[M+H]+",
        "mz": 728.5628,
        "ccs": 272.47
    },
    {
        "name": "PE(o34:01)",
        "adduct": "[M+Na]+",
        "mz": 726.5393,
        "ccs": 275.79
    },
    {
        "name": "PE(o34:02)",
        "adduct": "[M+Na]+",
        "mz": 724.5226,
        "ccs": 273.65
    },
    {
        "name": "PE(o34:03)",
        "adduct": "[M+Na]+",
        "mz": 722.5068,
        "ccs": 270.85
    },
    {
        "name": "PE(o36:01)",
        "adduct": "[M+Na]+",
        "mz": 754.5689,
        "ccs": 281.66
    },
    {
        "name": "PE(o36:02)",
        "adduct": "[M+Na]+",
        "mz": 752.5546,
        "ccs": 280.37
    },
    {
        "name": "PE(o36:03)",
        "adduct": "[M+Na]+",
        "mz": 750.5394,
        "ccs": 277.92
    },
    {
        "name": "PE(o38:03)",
        "adduct": "[M+Na]+",
        "mz": 778.5688,
        "ccs": 283.24
    },
    {
        "name": "PE(o32:01)",
        "adduct": "[M+2Na-H]+",
        "mz": 720.4904,
        "ccs": 268.35
    },
    {
        "name": "PE(o34:01)",
        "adduct": "[M+2Na-H]+",
        "mz": 748.5209,
        "ccs": 276.22
    },
    {
        "name": "PE(o34:02)",
        "adduct": "[M+2Na-H]+",
        "mz": 746.5049,
        "ccs": 273.55
    },
    {
        "name": "PE(o34:03)",
        "adduct": "[M+2Na-H]+",
        "mz": 744.4895,
        "ccs": 271.58
    },
    {
        "name": "PE(o36:01)",
        "adduct": "[M+2Na-H]+",
        "mz": 776.5526,
        "ccs": 283.23
    },
    {
        "name": "PE(o36:02)",
        "adduct": "[M+2Na-H]+",
        "mz": 774.5373,
        "ccs": 280.9
    },
    {
        "name": "PE(o36:03)",
        "adduct": "[M+2Na-H]+",
        "mz": 772.5239,
        "ccs": 279.47
    },
    {
        "name": "PE(o36:04)",
        "adduct": "[M+2Na-H]+",
        "mz": 770.5082,
        "ccs": 278.13
    },
    {
        "name": "PE(o38:02)",
        "adduct": "[M+2Na-H]+",
        "mz": 802.5709,
        "ccs": 289.33
    },
    {
        "name": "PE(o38:03)",
        "adduct": "[M+2Na-H]+",
        "mz": 800.5531,
        "ccs": 287.42
    },
    {
        "name": "PE(o38:04)",
        "adduct": "[M+2Na-H]+",
        "mz": 798.5382,
        "ccs": 284.68
    },
    {
        "name": "PE(o38:05)",
        "adduct": "[M+2Na-H]+",
        "mz": 796.5215,
        "ccs": 282.48
    },
    {
        "name": "PE(o38:06)",
        "adduct": "[M+2Na-H]+",
        "mz": 794.5074,
        "ccs": 280.85
    },
    {
        "name": "PE(o40:04)",
        "adduct": "[M+2Na-H]+",
        "mz": 826.5675,
        "ccs": 293.52
    },
    {
        "name": "PE(o40:06)",
        "adduct": "[M+2Na-H]+",
        "mz": 822.5357,
        "ccs": 288.19
    },
    {
        "name": "PE(o34:01)",
        "adduct": "[M-H]-",
        "mz": 700.5296,
        "ccs": 263.84
    },
    {
        "name": "PE(o36:00)",
        "adduct": "[M-H]-",
        "mz": 730.5708,
        "ccs": 271.66
    },
    {
        "name": "PE(o36:01)",
        "adduct": "[M-H]-",
        "mz": 728.5597,
        "ccs": 270.26
    },
    {
        "name": "PE(o36:02)",
        "adduct": "[M-H]-",
        "mz": 726.5481,
        "ccs": 268.96
    },
    {
        "name": "PS(o35:02)",
        "adduct": "[M+2Na-H]+",
        "mz": 804.5114,
        "ccs": 282.4
    }
]